ashberry/__init__.py
ashberry/generator.py
ashberry/main.py
ashberry-0.1.0.dist-info/LICENSE
ashberry-0.1.0.dist-info/METADATA
ashberry-0.1.0.dist-info/WHEEL
ashberry-0.1.0.dist-info/entry_points.txt
ashberry-0.1.0.dist-info/RECORD
